gsheeter/__init__.py
gsheeter/auth/auth.py
gsheeter/cache/cache.py
gsheeter/client/client.py
gsheeter/client/client_types.py
gsheeter/client/client_utils.py
gsheeter/drive/drive.py
gsheeter/drive/drive_endpoints.py
gsheeter/drive/drive_types.py
gsheeter/drive/file.py
gsheeter/drive/folder.py
gsheeter/environ/environ.py
gsheeter/lego/api.py
gsheeter/lego/exceptions.py
gsheeter/lego/funcs.py
gsheeter/lego/lego.py
gsheeter/lego/property.py
gsheeter/lego/types.py
gsheeter/spreadsheet/base.py
gsheeter/spreadsheet/chart.py
gsheeter/spreadsheet/sheet.py
gsheeter/spreadsheet/sheet_objects.py
gsheeter/spreadsheet/sheet_types.py
gsheeter/spreadsheet/sheet_utils.py
gsheeter/spreadsheet/sheets_endpoints.py
gsheeter/spreadsheet/sheets_enum.py
gsheeter/spreadsheet/spreadsheet.py
gsheeter-0.3.6.dist-info/licenses/LICENSE.txt
gsheeter-0.3.6.dist-info/WHEEL
gsheeter-0.3.6.dist-info/METADATA
gsheeter-0.3.6.dist-info/RECORD
