Metadata-Version: 2.4
Name: gsheeter
Version: 0.3.6
Summary: Google spreadsheet Python API Abstractor integrated with pandas
Keywords: spreadsheets,google-spreadsheets,google-sheets
Author-email: Yunjong Guk <haydenkuk@gmail.com>
Maintainer-email: Yunjong Guk <haydenkuk@gmail.com>
Requires-Python: >=3.9
Classifier: Programming Language :: Python :: 3
Classifier: License :: OSI Approved :: MIT License
Classifier: Operating System :: OS Independent
Classifier: Development Status :: 3 - Alpha
Classifier: Intended Audience :: Developers
Classifier: Intended Audience :: End Users/Desktop
Classifier: Intended Audience :: Science/Research
Classifier: Topic :: Office/Business :: Financial :: Spreadsheet
Classifier: Topic :: Software Development :: Libraries :: Python Modules
License-File: LICENSE.txt
Requires-Dist: asttokens>=3.0.0
Requires-Dist: build>=1.2.2.post1
Requires-Dist: cachetools>=5.5.2
Requires-Dist: certifi>=2025.1.31
Requires-Dist: charset-normalizer>=3.4.1
Requires-Dist: colorama>=0.4.6
Requires-Dist: dateparser>=1.2.1
Requires-Dist: et_xmlfile>=2.0.0
Requires-Dist: executing>=2.2.0
Requires-Dist: google-api-core>=2.24.2
Requires-Dist: google-api-python-client>=2.166.0
Requires-Dist: google-auth>=2.38.0
Requires-Dist: google-auth-httplib2>=0.2.0
Requires-Dist: google-auth-oauthlib>=1.2.1
Requires-Dist: googleapis-common-protos>=1.69.2
Requires-Dist: httplib2>=0.22.0
Requires-Dist: idna>=3.10
Requires-Dist: numpy>=2.2.4
Requires-Dist: oauthlib>=3.2.2
Requires-Dist: openpyxl>=3.1.5
Requires-Dist: packaging>=25.0
Requires-Dist: pandas>=2.2.3
Requires-Dist: proto-plus>=1.26.1
Requires-Dist: protobuf>=6.30.2
Requires-Dist: pyasn1>=0.6.1
Requires-Dist: pyasn1_modules>=0.4.2
Requires-Dist: Pygments>=2.19.1
Requires-Dist: pyparsing>=3.2.3
Requires-Dist: pyproject_hooks>=1.2.0
Requires-Dist: python-dateutil>=2.9.0.post0
Requires-Dist: pytz>=2025.2
Requires-Dist: regex>=2024.11.6
Requires-Dist: requests>=2.32.3
Requires-Dist: requests-oauthlib>=2.0.0
Requires-Dist: rsa>=4.9
Requires-Dist: six>=1.17.0
Requires-Dist: typing_extensions>=4.13.2
Requires-Dist: tzdata>=2025.2
Requires-Dist: tzlocal>=5.3.1
Requires-Dist: uritemplate>=4.1.1
Requires-Dist: urllib3>=2.4.0
Requires-Dist: XlsxWriter>=3.2.3
Project-URL: Documentation, https://github.com/haydenkuk/gsheeter/blob/main/README.md
Project-URL: Issues, https://github.com/haydenkuk/gsheeter/issues
Project-URL: Source, https://github.com/haydenkuk/gsheeter
